landspy/__init__.py
landspy/flow.py
landspy/functions.py
landspy/grid.py
landspy/hypsometry.py
landspy/network.py
landspy/swath.py
landspy-1.3.0.dist-info/licenses/LICENSE.txt
landspy-1.3.0.dist-info/METADATA
landspy-1.3.0.dist-info/WHEEL
landspy-1.3.0.dist-info/top_level.txt
landspy-1.3.0.dist-info/RECORD
