Metadata-Version: 2.4
Name: landspy
Version: 1.3.0
Summary: Python library for landscape analysis with DEMs
Home-page: https://github.com/geolovic/landspy
Author: J. Vicente Perez Pena
Author-email: geolovic@gmail.com
Project-URL: Bug Tracker, https://github.com/geolovic/landspylandspy/issues
Classifier: License :: OSI Approved :: MIT License
Classifier: Natural Language :: English
Classifier: Operating System :: OS Independent
Requires-Python: >=3.6
License-File: LICENSE.txt
Requires-Dist: GDAL
Requires-Dist: numpy
Requires-Dist: matplotlib
Requires-Dist: scikit-image
Requires-Dist: scipy
Requires-Dist: shapely
Dynamic: author
Dynamic: author-email
Dynamic: classifier
Dynamic: description
Dynamic: description-content-type
Dynamic: home-page
Dynamic: license-file
Dynamic: project-url
Dynamic: requires-dist
Dynamic: requires-python
Dynamic: summary
